[
  {
    "leftSelection": {
      "startRow": 5,
      "startCol": 8,
      "endRow": 5,
      "endCol": 87
    },
    "rightSelection": {
      "startRow": 6,
      "startCol": 8,
      "endRow": 6,
      "endCol": 53
    },
    "data": "ber_expression (this) (property_identifier)) (call",
    "pairedOccurrences": [
      {
        "sharedKmer": 14,
        "left": {
          "start": 724,
          "stop": 773,
          "index": 32
        },
        "right": {
          "start": 315,
          "stop": 364,
          "index": 13
        }
      }
    ]
  }
]